lsst/ctrl/bps/parsl/__init__.py
lsst/ctrl/bps/parsl/configuration.py
lsst/ctrl/bps/parsl/environment.py
lsst/ctrl/bps/parsl/job.py
lsst/ctrl/bps/parsl/service.py
lsst/ctrl/bps/parsl/site.py
lsst/ctrl/bps/parsl/version.py
lsst/ctrl/bps/parsl/workflow.py
lsst/ctrl/bps/parsl/sites/__init__.py
lsst/ctrl/bps/parsl/sites/ccin2p3.py
lsst/ctrl/bps/parsl/sites/local.py
lsst/ctrl/bps/parsl/sites/nersc.py
lsst/ctrl/bps/parsl/sites/princeton.py
lsst/ctrl/bps/parsl/sites/slac.py
lsst/ctrl/bps/parsl/sites/slurm.py
lsst/ctrl/bps/parsl/sites/torque.py
lsst/ctrl/bps/parsl/sites/work_queue.py
lsst_ctrl_bps_parsl-30.2026.300.dist-info/licenses/COPYRIGHT
lsst_ctrl_bps_parsl-30.2026.300.dist-info/licenses/LICENSE
lsst_ctrl_bps_parsl-30.2026.300.dist-info/licenses/bsd_license.txt
lsst_ctrl_bps_parsl-30.2026.300.dist-info/licenses/gpl-v3.0.txt
lsst_ctrl_bps_parsl-30.2026.300.dist-info/METADATA
lsst_ctrl_bps_parsl-30.2026.300.dist-info/WHEEL
lsst_ctrl_bps_parsl-30.2026.300.dist-info/top_level.txt
lsst_ctrl_bps_parsl-30.2026.300.dist-info/zip-safe
lsst_ctrl_bps_parsl-30.2026.300.dist-info/RECORD
